msgspec_click/__init__.py
msgspec_click/_core.py
msgspec_click/py.typed
msgspec_click-0.2.1.dist-info/METADATA
msgspec_click-0.2.1.dist-info/WHEEL
msgspec_click-0.2.1.dist-info/licenses/LICENSE.txt
msgspec_click-0.2.1.dist-info/RECORD
