Metadata-Version: 2.3
Name: msgspec-click
Version: 0.2.1
Summary: Generate Click options from msgspec types
Project-URL: Homepage, https://ofek.dev/msgspec-click/
Project-URL: Sponsor, https://github.com/sponsors/ofek
Project-URL: Changelog, https://ofek.dev/msgspec-click/changelog/
Project-URL: Tracker, https://github.com/ofek/msgspec-click/issues
Project-URL: Source, https://github.com/ofek/msgspec-click
Author-email: Ofek Lev <oss@ofek.dev>
License-Expression: MIT
License-File: LICENSE.txt
Keywords: click,msgspec
Classifier: Development Status :: 4 - Beta
Classifier: Programming Language :: Python
Classifier: Programming Language :: Python :: 3.8
Classifier: Programming Language :: Python :: 3.9
Classifier: Programming Language :: Python :: 3.10
Classifier: Programming Language :: Python :: 3.11
Classifier: Programming Language :: Python :: 3.12
Classifier: Programming Language :: Python :: Implementation :: CPython
Classifier: Programming Language :: Python :: Implementation :: PyPy
Requires-Python: >=3.8
Requires-Dist: click
Requires-Dist: msgspec
